simpleui/__init__.py
simpleui/admin.py
simpleui/apps.py
simpleui/forms.py
simpleui/widgets.py
simpleui/__pycache__/__init__.cpython-37.pyc
simpleui/__pycache__/__init__.cpython-38.pyc
simpleui/static/admin/simpleui-x/automatic/dicts.js
simpleui/static/admin/simpleui-x/automatic/segment.js
simpleui/static/admin/simpleui-x/css/base.css
simpleui/static/admin/simpleui-x/css/base.css.map
simpleui/static/admin/simpleui-x/css/base.less
simpleui/static/admin/simpleui-x/css/index.css
simpleui/static/admin/simpleui-x/css/index.css.map
simpleui/static/admin/simpleui-x/css/index.less
simpleui/static/admin/simpleui-x/css/login.css
simpleui/static/admin/simpleui-x/elementui/index.js
simpleui/static/admin/simpleui-x/elementui/locale/format.js
simpleui/static/admin/simpleui-x/elementui/locale/index.js
simpleui/static/admin/simpleui-x/elementui/locale/lang/af-ZA.js
simpleui/static/admin/simpleui-x/elementui/locale/lang/ar.js
simpleui/static/admin/simpleui-x/elementui/locale/lang/bg.js
simpleui/static/admin/simpleui-x/elementui/locale/lang/ca.js
simpleui/static/admin/simpleui-x/elementui/locale/lang/cs-CZ.js
simpleui/static/admin/simpleui-x/elementui/locale/lang/da.js
simpleui/static/admin/simpleui-x/elementui/locale/lang/de.js
simpleui/static/admin/simpleui-x/elementui/locale/lang/ee.js
simpleui/static/admin/simpleui-x/elementui/locale/lang/el.js
simpleui/static/admin/simpleui-x/elementui/locale/lang/en.js
simpleui/static/admin/simpleui-x/elementui/locale/lang/eo.js
simpleui/static/admin/simpleui-x/elementui/locale/lang/es.js
simpleui/static/admin/simpleui-x/elementui/locale/lang/eu.js
simpleui/static/admin/simpleui-x/elementui/locale/lang/fa.js
simpleui/static/admin/simpleui-x/elementui/locale/lang/fi.js
simpleui/static/admin/simpleui-x/elementui/locale/lang/fr.js
simpleui/static/admin/simpleui-x/elementui/locale/lang/he.js
simpleui/static/admin/simpleui-x/elementui/locale/lang/hr.js
simpleui/static/admin/simpleui-x/elementui/locale/lang/hu.js
django_simpleui_dev-2023.2.28.dist-info/LICENSE
django_simpleui_dev-2023.2.28.dist-info/METADATA
django_simpleui_dev-2023.2.28.dist-info/WHEEL
django_simpleui_dev-2023.2.28.dist-info/top_level.txt
django_simpleui_dev-2023.2.28.dist-info/RECORD
