Metadata-Version: 2.1
Name: django-simpleui-dev
Version: 2023.2.28
Summary: django admin theme 后台模板
Home-page: https://github.com/newpanjing/simpleui
Author: panjing
Author-email: newpanjing@icloud.com
License: Apache License 2.0
Classifier: Programming Language :: Python :: 3
Classifier: Operating System :: OS Independent
License-File: LICENSE
Requires-Dist: django
